{
  "db_name": "PostgreSQL",
  "query": "SELECT auto_join_enabled, target_channel\n\t\t\tFROM per_voice_channel_settings\n\t\t\tWHERE channel_id = $1",
  "describe": {
    "columns": [
      {
        "ordinal": 0,
        "name": "auto_join_enabled",
        "type_info": "Bool"
      },
      {
        "ordinal": 1,
        "name": "target_channel",
        "type_info": "Int8"
      }
    ],
    "parameters": {
      "Left": [
        "Int8"
      ]
    },
    "nullable": [
      false,
      true
    ]
  },
  "hash": "22768a2f355a842e9f609a897425324de4c212c1eec688ca5a75708f764635ac"
}
